click_extended/__init__.py
click_extended/classes.py
click_extended/errors.py
click_extended/types.py
click_extended/core/__init__.py
click_extended/core/decorators/__init__.py
click_extended/core/decorators/argument.py
click_extended/core/decorators/command.py
click_extended/core/decorators/context.py
click_extended/core/decorators/env.py
click_extended/core/decorators/group.py
click_extended/core/decorators/option.py
click_extended/core/decorators/prompt.py
click_extended/core/decorators/selection.py
click_extended/core/decorators/tag.py
click_extended/core/nodes/__init__.py
click_extended/core/nodes/_root_node.py
click_extended/core/nodes/argument_node.py
click_extended/core/nodes/child_node.py
click_extended/core/nodes/child_validation_node.py
click_extended/core/nodes/node.py
click_extended/core/nodes/option_node.py
click_extended/core/nodes/parent_node.py
click_extended/core/nodes/validation_node.py
click_extended/core/other/__init__.py
click_extended/core/other/_click_command.py
click_extended/core/other/_click_group.py
click_extended/core/other/_tree.py
click_extended/core/other/context.py
click_extended/core/other/get_context.py
click_extended/decorators/__init__.py
click_extended/decorators/check/__init__.py
click_extended/decorators/check/conflicts.py
click_extended/decorators/check/contains.py
click_extended/decorators/check/dependencies.py
click_extended/decorators/check/divisible_by.py
click_extended/decorators/check/ends_with.py
click_extended/decorators/check/exclusive.py
click_extended/decorators/check/falsy.py
click_extended/decorators/check/is_email.py
click_extended/decorators/check/is_hex_color.py
click_extended/decorators/check/is_hostname.py
click_extended/decorators/check/is_ipv4.py
click_extended/decorators/check/is_ipv6.py
click_extended/decorators/check/is_json.py
click_extended/decorators/check/is_mac_address.py
click_extended/decorators/check/is_negative.py
click_extended/decorators/check/is_non_zero.py
click_extended-1.0.9.dist-info/licenses/AUTHORS.md
click_extended-1.0.9.dist-info/licenses/LICENSE
click_extended-1.0.9.dist-info/METADATA
click_extended-1.0.9.dist-info/WHEEL
click_extended-1.0.9.dist-info/top_level.txt
click_extended-1.0.9.dist-info/RECORD
