Metadata-Version: 2.4
Name: click_extended
Version: 1.0.9
Summary: An extension to Click with additional features like automatic async support, aliasing and a modular decorator system.
Author-email: Marcus Fredriksson <marcus@marcusfredriksson.com>
License: MIT License
Project-URL: Homepage, https://github.com/marcusfrdk/click-extended
Project-URL: Repository, https://github.com/marcusfrdk/click-extended
Project-URL: Issues, https://github.com/marcusfrdk/click-extended/issues
Keywords: click,cli,command-line,alias,aliasing,command,group,decorator,terminal,console
Classifier: Intended Audience :: Developers
Classifier: License :: OSI Approved :: MIT License
Classifier: Operating System :: OS Independent
Classifier: Programming Language :: Python :: 3
Classifier: Programming Language :: Python :: 3.10
Classifier: Programming Language :: Python :: 3.11
Classifier: Programming Language :: Python :: 3.12
Classifier: Programming Language :: Python :: 3.13
Classifier: Programming Language :: Python :: 3.14
Classifier: Topic :: Software Development :: Libraries :: Python Modules
Classifier: Topic :: System :: Shells
Classifier: Topic :: Utilities
Classifier: Typing :: Typed
Requires-Python: >=3.10
License-File: LICENSE
License-File: AUTHORS.md
Requires-Dist: click>=8.3.0
Requires-Dist: python-dotenv>=1.2.1
Requires-Dist: pyyaml>=6.0.3
Requires-Dist: email-validator>=2.3.0
Requires-Dist: python-slugify>=8.0.4
Requires-Dist: tomli>=2.0.0; python_version < "3.11"
Provides-Extra: build
Requires-Dist: build; extra == "build"
Requires-Dist: twine; extra == "build"
Provides-Extra: dev
Requires-Dist: pytest>=8.4.2; extra == "dev"
Requires-Dist: pytest-cov>=7.0.0; extra == "dev"
Requires-Dist: pytest-asyncio>=1.2.0; extra == "dev"
Requires-Dist: mypy>=1.18.2; extra == "dev"
Requires-Dist: pylint>=3.0.0; extra == "dev"
Requires-Dist: isort>=5.12.0; extra == "dev"
Requires-Dist: black>=25.9.0; extra == "dev"
Requires-Dist: pre-commit>=4.3.0; extra == "dev"
Requires-Dist: types-PyYAML>=6.0.12.20250915; extra == "dev"
Requires-Dist: tomli>=2.0.0; extra == "dev"
Dynamic: license-file
